{
  "formatVersion": 1,
  "database": {
    "version": 6,
    "identityHash": "bb19a924935c27cb11adb25466611f1a",
    "entities": [
      {
        "tableName": "words",
        "createSql": "CREATE TABLE IF NOT EXISTS `${TABLE_NAME}` (`id` INTEGER PRIMARY KEY AUTOINCREMENT NOT NULL, `english` TEXT NOT NULL, `chinese` TEXT NOT NULL, `part_of_speech` TEXT NOT NULL, `phonetic` TEXT NOT NULL, `deck_id` INTEGER NOT NULL, `created_at` INTEGER NOT NULL, `correct_count` INTEGER NOT NULL, `wrong_count` INTEGER NOT NULL, `last_review_time` INTEGER NOT NULL, `next_review_time` INTEGER NOT NULL, `ease_factor` REAL NOT NULL, `interval_days` INTEGER NOT NULL, `repetition` INTEGER NOT NULL, `first_learn_date` INTEGER NOT NULL, `review_stage` INTEGER NOT NULL, `word_type` TEXT NOT NULL, `phrase_usage` TEXT, FOREIGN KEY(`deck_id`) REFERENCES `decks`(`id`) ON UPDATE NO ACTION ON DELETE CASCADE )",
        "fields": [
          {
            "fieldPath": "id",
            "columnName": "id",
            "affinity": "INTEGER",
            "notNull": true
          },
          {
            "fieldPath": "english",
            "columnName": "english",
            "affinity": "TEXT",
            "notNull": true
          },
          {
            "fieldPath": "chinese",
            "columnName": "chinese",
            "affinity": "TEXT",
            "notNull": true
          },
          {
            "fieldPath": "partOfSpeech",
            "columnName": "part_of_speech",
            "affinity": "TEXT",
            "notNull": true
          },
          {
            "fieldPath": "phonetic",
            "columnName": "phonetic",
            "affinity": "TEXT",
            "notNull": true
          },
          {
            "fieldPath": "deckId",
            "columnName": "deck_id",
            "affinity": "INTEGER",
            "notNull": true
          },
          {
            "fieldPath": "createdAt",
            "columnName": "created_at",
            "affinity": "INTEGER",
            "notNull": true
          },
          {
            "fieldPath": "correctCount",
            "columnName": "correct_count",
            "affinity": "INTEGER",
            "notNull": true
          },
          {
            "fieldPath": "wrongCount",
            "columnName": "wrong_count",
            "affinity": "INTEGER",
            "notNull": true
          },
          {
            "fieldPath": "lastReviewTime",
            "columnName": "last_review_time",
            "affinity": "INTEGER",
            "notNull": true
          },
          {
            "fieldPath": "nextReviewTime",
            "columnName": "next_review_time",
            "affinity": "INTEGER",
            "notNull": true
          },
          {
            "fieldPath": "easeFactor",
            "columnName": "ease_factor",
            "affinity": "REAL",
            "notNull": true
          },
          {
            "fieldPath": "intervalDays",
            "columnName": "interval_days",
            "affinity": "INTEGER",
            "notNull": true
          },
          {
            "fieldPath": "repetition",
            "columnName": "repetition",
            "affinity": "INTEGER",
            "notNull": true
          },
          {
            "fieldPath": "firstLearnDate",
            "columnName": "first_learn_date",
            "affinity": "INTEGER",
            "notNull": true
          },
          {
            "fieldPath": "reviewStage",
            "columnName": "review_stage",
            "affinity": "INTEGER",
            "notNull": true
          },
          {
            "fieldPath": "wordType",
            "columnName": "word_type",
            "affinity": "TEXT",
            "notNull": true
          },
          {
            "fieldPath": "phraseUsage",
            "columnName": "phrase_usage",
            "affinity": "TEXT",
            "notNull": false
          }
        ],
        "primaryKey": {
          "autoGenerate": true,
          "columnNames": [
            "id"
          ]
        },
        "indices": [
          {
            "name": "index_words_deck_id",
            "unique": false,
            "columnNames": [
              "deck_id"
            ],
            "orders": [],
            "createSql": "CREATE INDEX IF NOT EXISTS `index_words_deck_id` ON `${TABLE_NAME}` (`deck_id`)"
          }
        ],
        "foreignKeys": [
          {
            "table": "decks",
            "onDelete": "CASCADE",
            "onUpdate": "NO ACTION",
            "columns": [
              "deck_id"
            ],
            "referencedColumns": [
              "id"
            ]
          }
        ]
      },
      {
        "tableName": "decks",
        "createSql": "CREATE TABLE IF NOT EXISTS `${TABLE_NAME}` (`id` INTEGER PRIMARY KEY AUTOINCREMENT NOT NULL, `name` TEXT NOT NULL, `description` TEXT NOT NULL, `word_count` INTEGER NOT NULL, `created_at` INTEGER NOT NULL, `updated_at` INTEGER NOT NULL, `is_active` INTEGER NOT NULL, `deck_type` TEXT NOT NULL)",
        "fields": [
          {
            "fieldPath": "id",
            "columnName": "id",
            "affinity": "INTEGER",
            "notNull": true
          },
          {
            "fieldPath": "name",
            "columnName": "name",
            "affinity": "TEXT",
            "notNull": true
          },
          {
            "fieldPath": "description",
            "columnName": "description",
            "affinity": "TEXT",
            "notNull": true
          },
          {
            "fieldPath": "wordCount",
            "columnName": "word_count",
            "affinity": "INTEGER",
            "notNull": true
          },
          {
            "fieldPath": "createdAt",
            "columnName": "created_at",
            "affinity": "INTEGER",
            "notNull": true
          },
          {
            "fieldPath": "updatedAt",
            "columnName": "updated_at",
            "affinity": "INTEGER",
            "notNull": true
          },
          {
            "fieldPath": "isActive",
            "columnName": "is_active",
            "affinity": "INTEGER",
            "notNull": true
          },
          {
            "fieldPath": "deckType",
            "columnName": "deck_type",
            "affinity": "TEXT",
            "notNull": true
          }
        ],
        "primaryKey": {
          "autoGenerate": true,
          "columnNames": [
            "id"
          ]
        },
        "indices": [],
        "foreignKeys": []
      },
      {
        "tableName": "study_sessions",
        "createSql": "CREATE TABLE IF NOT EXISTS `${TABLE_NAME}` (`id` INTEGER PRIMARY KEY AUTOINCREMENT NOT NULL, `deck_id` INTEGER NOT NULL, `planned_count` INTEGER NOT NULL, `completed_count` INTEGER NOT NULL, `correct_count` INTEGER NOT NULL, `start_time` INTEGER NOT NULL, `end_time` INTEGER, `is_completed` INTEGER NOT NULL)",
        "fields": [
          {
            "fieldPath": "id",
            "columnName": "id",
            "affinity": "INTEGER",
            "notNull": true
          },
          {
            "fieldPath": "deckId",
            "columnName": "deck_id",
            "affinity": "INTEGER",
            "notNull": true
          },
          {
            "fieldPath": "plannedCount",
            "columnName": "planned_count",
            "affinity": "INTEGER",
            "notNull": true
          },
          {
            "fieldPath": "completedCount",
            "columnName": "completed_count",
            "affinity": "INTEGER",
            "notNull": true
          },
          {
            "fieldPath": "correctCount",
            "columnName": "correct_count",
            "affinity": "INTEGER",
            "notNull": true
          },
          {
            "fieldPath": "startTime",
            "columnName": "start_time",
            "affinity": "INTEGER",
            "notNull": true
          },
          {
            "fieldPath": "endTime",
            "columnName": "end_time",
            "affinity": "INTEGER",
            "notNull": false
          },
          {
            "fieldPath": "isCompleted",
            "columnName": "is_completed",
            "affinity": "INTEGER",
            "notNull": true
          }
        ],
        "primaryKey": {
          "autoGenerate": true,
          "columnNames": [
            "id"
          ]
        },
        "indices": [],
        "foreignKeys": []
      },
      {
        "tableName": "settings",
        "createSql": "CREATE TABLE IF NOT EXISTS `${TABLE_NAME}` (`id` INTEGER NOT NULL, `fontSize` REAL NOT NULL, `backgroundColor` INTEGER NOT NULL, `primaryColor` INTEGER NOT NULL, `themeMode` TEXT NOT NULL, `isAutoBackup` INTEGER NOT NULL, `backupPath` TEXT NOT NULL, `studyReminder` INTEGER NOT NULL, `reminderTime` TEXT NOT NULL, `reminderTimeMillis` INTEGER NOT NULL, `reminderType` TEXT NOT NULL, `calendarEventId` INTEGER, `alarmRequestCode` INTEGER, PRIMARY KEY(`id`))",
        "fields": [
          {
            "fieldPath": "id",
            "columnName": "id",
            "affinity": "INTEGER",
            "notNull": true
          },
          {
            "fieldPath": "fontSize",
            "columnName": "fontSize",
            "affinity": "REAL",
            "notNull": true
          },
          {
            "fieldPath": "backgroundColor",
            "columnName": "backgroundColor",
            "affinity": "INTEGER",
            "notNull": true
          },
          {
            "fieldPath": "primaryColor",
            "columnName": "primaryColor",
            "affinity": "INTEGER",
            "notNull": true
          },
          {
            "fieldPath": "themeMode",
            "columnName": "themeMode",
            "affinity": "TEXT",
            "notNull": true
          },
          {
            "fieldPath": "isAutoBackup",
            "columnName": "isAutoBackup",
            "affinity": "INTEGER",
            "notNull": true
          },
          {
            "fieldPath": "backupPath",
            "columnName": "backupPath",
            "affinity": "TEXT",
            "notNull": true
          },
          {
            "fieldPath": "studyReminder",
            "columnName": "studyReminder",
            "affinity": "INTEGER",
            "notNull": true
          },
          {
            "fieldPath": "reminderTime",
            "columnName": "reminderTime",
            "affinity": "TEXT",
            "notNull": true
          },
          {
            "fieldPath": "reminderTimeMillis",
            "columnName": "reminderTimeMillis",
            "affinity": "INTEGER",
            "notNull": true
          },
          {
            "fieldPath": "reminderType",
            "columnName": "reminderType",
            "affinity": "TEXT",
            "notNull": true
          },
          {
            "fieldPath": "calendarEventId",
            "columnName": "calendarEventId",
            "affinity": "INTEGER",
            "notNull": false
          },
          {
            "fieldPath": "alarmRequestCode",
            "columnName": "alarmRequestCode",
            "affinity": "INTEGER",
            "notNull": false
          }
        ],
        "primaryKey": {
          "autoGenerate": false,
          "columnNames": [
            "id"
          ]
        },
        "indices": [],
        "foreignKeys": []
      },
      {
        "tableName": "questions",
        "createSql": "CREATE TABLE IF NOT EXISTS `${TABLE_NAME}` (`id` INTEGER PRIMARY KEY AUTOINCREMENT NOT NULL, `deck_id` INTEGER NOT NULL, `question_type` TEXT NOT NULL, `question_text` TEXT NOT NULL, `option_a` TEXT, `option_b` TEXT, `option_c` TEXT, `option_d` TEXT, `correct_answer` TEXT NOT NULL, `created_at` INTEGER NOT NULL, `correct_count` INTEGER NOT NULL, `wrong_count` INTEGER NOT NULL, `last_review_time` INTEGER NOT NULL, `next_review_time` INTEGER NOT NULL, `ease_factor` REAL NOT NULL, `interval_days` INTEGER NOT NULL, `repetition` INTEGER NOT NULL, `first_learn_date` INTEGER NOT NULL, `review_stage` INTEGER NOT NULL, FOREIGN KEY(`deck_id`) REFERENCES `decks`(`id`) ON UPDATE NO ACTION ON DELETE CASCADE )",
        "fields": [
          {
            "fieldPath": "id",
            "columnName": "id",
            "affinity": "INTEGER",
            "notNull": true
          },
          {
            "fieldPath": "deckId",
            "columnName": "deck_id",
            "affinity": "INTEGER",
            "notNull": true
          },
          {
            "fieldPath": "questionType",
            "columnName": "question_type",
            "affinity": "TEXT",
            "notNull": true
          },
          {
            "fieldPath": "questionText",
            "columnName": "question_text",
            "affinity": "TEXT",
            "notNull": true
          },
          {
            "fieldPath": "optionA",
            "columnName": "option_a",
            "affinity": "TEXT",
            "notNull": false
          },
          {
            "fieldPath": "optionB",
            "columnName": "option_b",
            "affinity": "TEXT",
            "notNull": false
          },
          {
            "fieldPath": "optionC",
            "columnName": "option_c",
            "affinity": "TEXT",
            "notNull": false
          },
          {
            "fieldPath": "optionD",
            "columnName": "option_d",
            "affinity": "TEXT",
            "notNull": false
          },
          {
            "fieldPath": "correctAnswer",
            "columnName": "correct_answer",
            "affinity": "TEXT",
            "notNull": true
          },
          {
            "fieldPath": "createdAt",
            "columnName": "created_at",
            "affinity": "INTEGER",
            "notNull": true
          },
          {
            "fieldPath": "correctCount",
            "columnName": "correct_count",
            "affinity": "INTEGER",
            "notNull": true
          },
          {
            "fieldPath": "wrongCount",
            "columnName": "wrong_count",
            "affinity": "INTEGER",
            "notNull": true
          },
          {
            "fieldPath": "lastReviewTime",
            "columnName": "last_review_time",
            "affinity": "INTEGER",
            "notNull": true
          },
          {
            "fieldPath": "nextReviewTime",
            "columnName": "next_review_time",
            "affinity": "INTEGER",
            "notNull": true
          },
          {
            "fieldPath": "easeFactor",
            "columnName": "ease_factor",
            "affinity": "REAL",
            "notNull": true
          },
          {
            "fieldPath": "intervalDays",
            "columnName": "interval_days",
            "affinity": "INTEGER",
            "notNull": true
          },
          {
            "fieldPath": "repetition",
            "columnName": "repetition",
            "affinity": "INTEGER",
            "notNull": true
          },
          {
            "fieldPath": "firstLearnDate",
            "columnName": "first_learn_date",
            "affinity": "INTEGER",
            "notNull": true
          },
          {
            "fieldPath": "reviewStage",
            "columnName": "review_stage",
            "affinity": "INTEGER",
            "notNull": true
          }
        ],
        "primaryKey": {
          "autoGenerate": true,
          "columnNames": [
            "id"
          ]
        },
        "indices": [
          {
            "name": "index_questions_deck_id",
            "unique": false,
            "columnNames": [
              "deck_id"
            ],
            "orders": [],
            "createSql": "CREATE INDEX IF NOT EXISTS `index_questions_deck_id` ON `${TABLE_NAME}` (`deck_id`)"
          }
        ],
        "foreignKeys": [
          {
            "table": "decks",
            "onDelete": "CASCADE",
            "onUpdate": "NO ACTION",
            "columns": [
              "deck_id"
            ],
            "referencedColumns": [
              "id"
            ]
          }
        ]
      }
    ],
    "views": [],
    "setupQueries": [
      "CREATE TABLE IF NOT EXISTS room_master_table (id INTEGER PRIMARY KEY,identity_hash TEXT)",
      "INSERT OR REPLACE INTO room_master_table (id,identity_hash) VALUES(42, 'bb19a924935c27cb11adb25466611f1a')"
    ]
  }
}